[{"name":"Mundang","alpha_3":"mua","scope":"I","type":"L","inverted_name":null,"alpha_2":null},{"name":"Mubi","alpha_3":"mub","scope":"I","type":"L","inverted_name":null,"alpha_2":null},{"name":"Ajumbu","alpha_3":"muc","scope":"I","type":"L","inverted_name":null,"alpha_2":null},{"name":"Mednyj Aleut","alpha_3":"mud","scope":"I","type":"L","inverted_name":"Aleut, Mednyj","alpha_2":null},{"name":"Media Lengua","alpha_3":"mue","scope":"I","type":"L","inverted_name":null,"alpha_2":null},{"name":"Musgu","alpha_3":"mug","scope":"I","type":"L","inverted_name":null,"alpha_2":null},{"name":"M\u00fcnd\u00fc","alpha_3":"muh","scope":"I","type":"L","inverted_name":null,"alpha_2":null},{"name":"Musi","alpha_3":"mui","scope":"I","type":"L","inverted_name":null,"alpha_2":null},{"name":"Mabire","alpha_3":"muj","scope":"I","type":"L","inverted_name":null,"alpha_2":null},{"name":"Mugom","alpha_3":"muk","scope":"I","type":"L","inverted_name":null,"alpha_2":null},{"name":"Multiple languages","alpha_3":"mul","scope":"S","type":"S","inverted_name":null,"alpha_2":null},{"name":"Maiwala","alpha_3":"mum","scope":"I","type":"L","inverted_name":null,"alpha_2":null},{"name":"Nyong","alpha_3":"muo","scope":"I","type":"L","inverted_name":null,"alpha_2":null},{"name":"Malvi","alpha_3":"mup","scope":"I","type":"L","inverted_name":null,"alpha_2":null},{"name":"Eastern Xiangxi Miao","alpha_3":"muq","scope":"I","type":"L","inverted_name":"Miao, Eastern Xiangxi","alpha_2":null},{"name":"Murle","alpha_3":"mur","scope":"I","type":"L","inverted_name":null,"alpha_2":null},{"name":"Creek","alpha_3":"mus","scope":"I","type":"L","inverted_name":null,"alpha_2":null},{"name":"Western Muria","alpha_3":"mut","scope":"I","type":"L","inverted_name":"Muria, Western","alpha_2":null},{"name":"Yaaku","alpha_3":"muu","scope":"I","type":"L","inverted_name":null,"alpha_2":null},{"name":"Muthuvan","alpha_3":"muv","scope":"I","type":"L","inverted_name":null,"alpha_2":null},{"name":"Bo-Ung","alpha_3":"mux","scope":"I","type":"L","inverted_name":null,"alpha_2":null},{"name":"Muyang","alpha_3":"muy","scope":"I","type":"L","inverted_name":null,"alpha_2":null},{"name":"Mursi","alpha_3":"muz","scope":"I","type":"L","inverted_name":null,"alpha_2":null}]