[{"name":"Wewaw","alpha_3":"wea","scope":"I","type":"E","inverted_name":null,"alpha_2":null},{"name":"W\u00e8 Western","alpha_3":"wec","scope":"I","type":"L","inverted_name":null,"alpha_2":null},{"name":"Wedau","alpha_3":"wed","scope":"I","type":"L","inverted_name":null,"alpha_2":null},{"name":"Wergaia","alpha_3":"weg","scope":"I","type":"L","inverted_name":null,"alpha_2":null},{"name":"Weh","alpha_3":"weh","scope":"I","type":"L","inverted_name":null,"alpha_2":null},{"name":"Kiunum","alpha_3":"wei","scope":"I","type":"L","inverted_name":null,"alpha_2":null},{"name":"Weme Gbe","alpha_3":"wem","scope":"I","type":"L","inverted_name":"Gbe, Weme","alpha_2":null},{"name":"Wemale","alpha_3":"weo","scope":"I","type":"L","inverted_name":null,"alpha_2":null},{"name":"Westphalien","alpha_3":"wep","scope":"I","type":"L","inverted_name":null,"alpha_2":null},{"name":"Weri","alpha_3":"wer","scope":"I","type":"L","inverted_name":null,"alpha_2":null},{"name":"Cameroon Pidgin","alpha_3":"wes","scope":"I","type":"L","inverted_name":"Pidgin, Cameroon","alpha_2":null},{"name":"Perai","alpha_3":"wet","scope":"I","type":"L","inverted_name":null,"alpha_2":null},{"name":"Rawngtu Chin","alpha_3":"weu","scope":"I","type":"L","inverted_name":"Chin, Rawngtu","alpha_2":null},{"name":"Wejewa","alpha_3":"wew","scope":"I","type":"L","inverted_name":null,"alpha_2":null}]