[{"code":"LK-1","name":"Basn\u0101hira pa\u1e37\u0101ta","type":"Province"},{"code":"LK-11","name":"K\u014f\u1e37amba","type":"District"},{"code":"LK-12","name":"Gampaha","type":"District"},{"code":"LK-13","name":"Ka\u1e37utara","type":"District"},{"code":"LK-2","name":"Madhyama pa\u1e37\u0101ta","type":"Province"},{"code":"LK-21","name":"Mahanuvara","type":"District"},{"code":"LK-22","name":"M\u0101tale","type":"District"},{"code":"LK-23","name":"Nuvara \u0114liya","type":"District"},{"code":"LK-3","name":"Daku\u1e47u pa\u1e37\u0101ta","type":"Province"},{"code":"LK-31","name":"G\u0101lla","type":"District"},{"code":"LK-32","name":"M\u0101tara","type":"District"},{"code":"LK-33","name":"Hambant\u014f\u1e6da","type":"District"},{"code":"LK-4","name":"Uturu pa\u1e37\u0101ta","type":"Province"},{"code":"LK-41","name":"Y\u0101panaya","type":"District"},{"code":"LK-42","name":"Kilin\u014fchchi","type":"District"},{"code":"LK-43","name":"Mann\u0101rama","type":"District"},{"code":"LK-44","name":"Vavuniy\u0101va","type":"District"},{"code":"LK-45","name":"Mulativ","type":"District"},{"code":"LK-5","name":"N\u00e6\u0306g\u0115nahira pa\u1e37\u0101ta","type":"Province"},{"code":"LK-51","name":"Ma\u1e0dakalapuva","type":"District"},{"code":"LK-52","name":"Amp\u0101ara","type":"District"},{"code":"LK-53","name":"Triku\u1e47\u0101malaya","type":"District"},{"code":"LK-6","name":"Vayamba pa\u1e37\u0101ta","type":"Province"},{"code":"LK-61","name":"Kuru\u1e47\u00e6gala","type":"District"},{"code":"LK-62","name":"Puttalama","type":"District"},{"code":"LK-7","name":"Uturum\u00e6\u0306da pa\u1e37\u0101ta","type":"Province"},{"code":"LK-71","name":"Anur\u0101dhapura","type":"District"},{"code":"LK-72","name":"P\u014f\u1e37\u014fnnaruva","type":"District"},{"code":"LK-8","name":"\u016ava pa\u1e37\u0101ta","type":"Province"},{"code":"LK-81","name":"Badulla","type":"District"},{"code":"LK-82","name":"M\u014f\u1e47ar\u0101gala","type":"District"},{"code":"LK-9","name":"Sabaragamuva pa\u1e37\u0101ta","type":"Province"},{"code":"LK-91","name":"Ratnapura","type":"District"},{"code":"LK-92","name":"K\u00e6galla","type":"District"}]