[{"name":"Awar","alpha_3":"aya","scope":"I","type":"L","inverted_name":null,"alpha_2":null},{"name":"Ayizo Gbe","alpha_3":"ayb","scope":"I","type":"L","inverted_name":"Gbe, Ayizo","alpha_2":null},{"name":"Southern Aymara","alpha_3":"ayc","scope":"I","type":"L","inverted_name":"Aymara, Southern","alpha_2":null},{"name":"Ayabadhu","alpha_3":"ayd","scope":"I","type":"E","inverted_name":null,"alpha_2":null},{"name":"Ayere","alpha_3":"aye","scope":"I","type":"L","inverted_name":null,"alpha_2":null},{"name":"Ginyanga","alpha_3":"ayg","scope":"I","type":"L","inverted_name":null,"alpha_2":null},{"name":"Hadrami Arabic","alpha_3":"ayh","scope":"I","type":"L","inverted_name":"Arabic, Hadrami","alpha_2":null},{"name":"Leyigha","alpha_3":"ayi","scope":"I","type":"L","inverted_name":null,"alpha_2":null},{"name":"Akuku","alpha_3":"ayk","scope":"I","type":"L","inverted_name":null,"alpha_2":null},{"name":"Libyan Arabic","alpha_3":"ayl","scope":"I","type":"L","inverted_name":"Arabic, Libyan","alpha_2":null},{"name":"Aymara","alpha_3":"aym","scope":"M","type":"L","inverted_name":null,"alpha_2":"ay"},{"name":"Sanaani Arabic","alpha_3":"ayn","scope":"I","type":"L","inverted_name":"Arabic, Sanaani","alpha_2":null},{"name":"Ayoreo","alpha_3":"ayo","scope":"I","type":"L","inverted_name":null,"alpha_2":null},{"name":"North Mesopotamian Arabic","alpha_3":"ayp","scope":"I","type":"L","inverted_name":"Arabic, North Mesopotamian","alpha_2":null},{"name":"Ayi (Papua New Guinea)","alpha_3":"ayq","scope":"I","type":"L","inverted_name":null,"alpha_2":null},{"name":"Central Aymara","alpha_3":"ayr","scope":"I","type":"L","inverted_name":"Aymara, Central","alpha_2":null},{"name":"Sorsogon Ayta","alpha_3":"ays","scope":"I","type":"L","inverted_name":"Ayta, Sorsogon","alpha_2":null},{"name":"Magbukun Ayta","alpha_3":"ayt","scope":"I","type":"L","inverted_name":"Ayta, Magbukun","alpha_2":null},{"name":"Ayu","alpha_3":"ayu","scope":"I","type":"L","inverted_name":null,"alpha_2":null},{"name":"Tayabas Ayta","alpha_3":"ayy","scope":"I","type":"E","inverted_name":"Ayta, Tayabas","alpha_2":null},{"name":"Mai Brat","alpha_3":"ayz","scope":"I","type":"L","inverted_name":null,"alpha_2":null}]