[{"name":"Etebi","alpha_3":"etb","scope":"I","type":"L","inverted_name":null,"alpha_2":null},{"name":"Etchemin","alpha_3":"etc","scope":"I","type":"E","inverted_name":null,"alpha_2":null},{"name":"Ethiopian Sign Language","alpha_3":"eth","scope":"I","type":"L","inverted_name":null,"alpha_2":null},{"name":"Eton (Vanuatu)","alpha_3":"etn","scope":"I","type":"L","inverted_name":null,"alpha_2":null},{"name":"Eton (Cameroon)","alpha_3":"eto","scope":"I","type":"L","inverted_name":null,"alpha_2":null},{"name":"Edolo","alpha_3":"etr","scope":"I","type":"L","inverted_name":null,"alpha_2":null},{"name":"Yekhee","alpha_3":"ets","scope":"I","type":"L","inverted_name":null,"alpha_2":null},{"name":"Etruscan","alpha_3":"ett","scope":"I","type":"A","inverted_name":null,"alpha_2":null},{"name":"Ejagham","alpha_3":"etu","scope":"I","type":"L","inverted_name":null,"alpha_2":null},{"name":"Eten","alpha_3":"etx","scope":"I","type":"L","inverted_name":null,"alpha_2":null},{"name":"Semimi","alpha_3":"etz","scope":"I","type":"L","inverted_name":null,"alpha_2":null}]