[{"name":"Northern Qiandong Miao","alpha_3":"hea","scope":"I","type":"L","inverted_name":"Miao, Northern Qiandong","alpha_2":null},{"name":"Hebrew","alpha_3":"heb","scope":"I","type":"L","inverted_name":null,"alpha_2":"he"},{"name":"Herd\u00e9","alpha_3":"hed","scope":"I","type":"L","inverted_name":null,"alpha_2":null},{"name":"Helong","alpha_3":"heg","scope":"I","type":"L","inverted_name":null,"alpha_2":null},{"name":"Hehe","alpha_3":"heh","scope":"I","type":"L","inverted_name":null,"alpha_2":null},{"name":"Heiltsuk","alpha_3":"hei","scope":"I","type":"L","inverted_name":null,"alpha_2":null},{"name":"Hemba","alpha_3":"hem","scope":"I","type":"L","inverted_name":null,"alpha_2":null},{"name":"Herero","alpha_3":"her","scope":"I","type":"L","inverted_name":null,"alpha_2":"hz"}]