[{"name":"S\u00e1liba","alpha_3":"slc","scope":"I","type":"L","inverted_name":null,"alpha_2":null},{"name":"Sissala","alpha_3":"sld","scope":"I","type":"L","inverted_name":null,"alpha_2":null},{"name":"Sholaga","alpha_3":"sle","scope":"I","type":"L","inverted_name":null,"alpha_2":null},{"name":"Swiss-Italian Sign Language","alpha_3":"slf","scope":"I","type":"L","inverted_name":null,"alpha_2":null},{"name":"Selungai Murut","alpha_3":"slg","scope":"I","type":"L","inverted_name":null,"alpha_2":null},{"name":"Southern Puget Sound Salish","alpha_3":"slh","scope":"I","type":"L","inverted_name":"Salish, Southern Puget Sound","alpha_2":null},{"name":"Lower Silesian","alpha_3":"sli","scope":"I","type":"L","inverted_name":"Silesian, Lower","alpha_2":null},{"name":"Salum\u00e1","alpha_3":"slj","scope":"I","type":"L","inverted_name":null,"alpha_2":null},{"name":"Slovak","alpha_3":"slk","scope":"I","type":"L","inverted_name":null,"alpha_2":"sk"},{"name":"Salt-Yui","alpha_3":"sll","scope":"I","type":"L","inverted_name":null,"alpha_2":null},{"name":"Pangutaran Sama","alpha_3":"slm","scope":"I","type":"L","inverted_name":"Sama, Pangutaran","alpha_2":null},{"name":"Salinan","alpha_3":"sln","scope":"I","type":"E","inverted_name":null,"alpha_2":null},{"name":"Lamaholot","alpha_3":"slp","scope":"I","type":"L","inverted_name":null,"alpha_2":null},{"name":"Salchuq","alpha_3":"slq","scope":"I","type":"L","inverted_name":null,"alpha_2":null},{"name":"Salar","alpha_3":"slr","scope":"I","type":"L","inverted_name":null,"alpha_2":null},{"name":"Singapore Sign Language","alpha_3":"sls","scope":"I","type":"L","inverted_name":null,"alpha_2":null},{"name":"Sila","alpha_3":"slt","scope":"I","type":"L","inverted_name":null,"alpha_2":null},{"name":"Selaru","alpha_3":"slu","scope":"I","type":"L","inverted_name":null,"alpha_2":null},{"name":"Slovenian","alpha_3":"slv","scope":"I","type":"L","inverted_name":null,"alpha_2":"sl"},{"name":"Sialum","alpha_3":"slw","scope":"I","type":"L","inverted_name":null,"alpha_2":null},{"name":"Salampasu","alpha_3":"slx","scope":"I","type":"L","inverted_name":null,"alpha_2":null},{"name":"Selayar","alpha_3":"sly","scope":"I","type":"L","inverted_name":null,"alpha_2":null},{"name":"Ma'ya","alpha_3":"slz","scope":"I","type":"L","inverted_name":null,"alpha_2":null}]