[{"name":"Vaagri Booli","alpha_3":"vaa","scope":"I","type":"L","inverted_name":null,"alpha_2":null},{"name":"Vale","alpha_3":"vae","scope":"I","type":"L","inverted_name":null,"alpha_2":null},{"name":"Vafsi","alpha_3":"vaf","scope":"I","type":"L","inverted_name":null,"alpha_2":null},{"name":"Vagla","alpha_3":"vag","scope":"I","type":"L","inverted_name":null,"alpha_2":null},{"name":"Varhadi-Nagpuri","alpha_3":"vah","scope":"I","type":"L","inverted_name":null,"alpha_2":null},{"name":"Vai","alpha_3":"vai","scope":"I","type":"L","inverted_name":null,"alpha_2":null},{"name":"Sekele","alpha_3":"vaj","scope":"I","type":"L","inverted_name":null,"alpha_2":null},{"name":"Vehes","alpha_3":"val","scope":"I","type":"L","inverted_name":null,"alpha_2":null},{"name":"Vanimo","alpha_3":"vam","scope":"I","type":"L","inverted_name":null,"alpha_2":null},{"name":"Valman","alpha_3":"van","scope":"I","type":"L","inverted_name":null,"alpha_2":null},{"name":"Vao","alpha_3":"vao","scope":"I","type":"L","inverted_name":null,"alpha_2":null},{"name":"Vaiphei","alpha_3":"vap","scope":"I","type":"L","inverted_name":null,"alpha_2":null},{"name":"Huarijio","alpha_3":"var","scope":"I","type":"L","inverted_name":null,"alpha_2":null},{"name":"Vasavi","alpha_3":"vas","scope":"I","type":"L","inverted_name":null,"alpha_2":null},{"name":"Vanuma","alpha_3":"vau","scope":"I","type":"L","inverted_name":null,"alpha_2":null},{"name":"Varli","alpha_3":"vav","scope":"I","type":"L","inverted_name":null,"alpha_2":null},{"name":"Wayu","alpha_3":"vay","scope":"I","type":"L","inverted_name":null,"alpha_2":null}]